pythonUtils/__init__.py
pythonUtils/converter.py
pythonUtils/measure.py
pythonUtils/parallel.py
pythonUtils/plugins.py
pythonUtils/time.py
pythonUtility-0.3.1.dist-info/METADATA
pythonUtility-0.3.1.dist-info/WHEEL
pythonUtility-0.3.1.dist-info/top_level.txt
pythonUtility-0.3.1.dist-info/RECORD
