Metadata-Version: 2.1
Name: pythonUtility
Version: 0.3.1
Summary: Python utility collection
Home-page: https://git.widmer.me/project/pythonUtil
Author: Joel Widmer
Author-email: joel.widmer.wj@gmail.com
License: BSD
Keywords: Utilities
Platform: UNKNOWN
Classifier: Development Status :: 2 - Pre-Alpha
Classifier: Topic :: Utilities
Classifier: License :: OSI Approved :: BSD License
